fdpass
postconfirm
