Metadata-Version: 1.1
Name: postconfirm
Version: 0.42.0
Summary: Mailing list posting confirmation daemon
Home-page: UNKNOWN
Author: Henrik Levkowetz
Author-email: henrik@levkowetz.com
License: Simplified BSD
Keywords: Mailing list posting confirmation daemon
Platform: UNKNOWN
Classifier: Development Status :: 3 - Alpha
Classifier: Intended Audience :: Other Audience
Classifier: Topic :: Communications :: Email
Classifier: License :: OSI Approved :: BSD License
Classifier: Programming Language :: Python :: 2
Classifier: Programming Language :: Python :: 2.7
